README.txt
setup.py
jprimee/__init__.py
jprimee.egg-info/PKG-INFO
jprimee.egg-info/SOURCES.txt
jprimee.egg-info/dependency_links.txt
jprimee.egg-info/top_level.txt