Metadata-Version: 1.1
Name: jprimee
Version: 0.0.1
Summary: Checks whether number is prime or not
Home-page: UNKNOWN
Author: Jiganesh Patil
Author-email: jiganeshpatil01071999@gmail.com
License: MIT
Keywords: prime
Platform: UNKNOWN
Classifier: Development Status :: 5 - Production/Stable
Classifier: Intended Audience :: Education
Classifier: Operating System :: Microsoft :: Windows :: Windows 10
Classifier: License :: OSI Approved :: MIT License
Classifier: Programming Language :: Python :: 3
